{
  "version": 2,
  "extractor": "papercropper",
  "tables": [
    {
      "url": "assets/tables/arxiv/2606.20844v1/table-001.webp",
      "caption": "",
      "page": 0,
      "index": 1,
      "width": 1350,
      "height": 453,
      "label": "Table"
    },
    {
      "url": "assets/tables/arxiv/2606.20844v1/table-002.webp",
      "caption": "",
      "page": 0,
      "index": 2,
      "width": 1345,
      "height": 232,
      "label": "Table"
    },
    {
      "url": "assets/tables/arxiv/2606.20844v1/table-003.webp",
      "caption": "",
      "page": 0,
      "index": 3,
      "width": 1762,
      "height": 290,
      "label": "Table"
    },
    {
      "url": "assets/tables/arxiv/2606.20844v1/table-004.webp",
      "caption": "",
      "page": 0,
      "index": 4,
      "width": 1739,
      "height": 290,
      "label": "Table"
    },
    {
      "url": "assets/tables/arxiv/2606.20844v1/table-005.webp",
      "caption": "",
      "page": 0,
      "index": 5,
      "width": 976,
      "height": 508,
      "label": "Table"
    },
    {
      "url": "assets/tables/arxiv/2606.20844v1/table-006.webp",
      "caption": "",
      "page": 0,
      "index": 6,
      "width": 1737,
      "height": 659,
      "label": "Table"
    },
    {
      "url": "assets/tables/arxiv/2606.20844v1/table-007.webp",
      "caption": "",
      "page": 0,
      "index": 7,
      "width": 946,
      "height": 802,
      "label": "Table"
    },
    {
      "url": "assets/tables/arxiv/2606.20844v1/table-008.webp",
      "caption": "",
      "page": 0,
      "index": 8,
      "width": 1560,
      "height": 1885,
      "label": "Table"
    }
  ]
}