{
  "version": 2,
  "extractor": "pdffigures2",
  "figures": [
    {
      "url": "assets/figures/arxiv/2605.09468v1/fig-001.webp",
      "caption": "Figure 1: Comparison of CDPR and Existing Paradigms.",
      "page": 1,
      "index": 1,
      "width": 460,
      "height": 527
    },
    {
      "url": "assets/figures/arxiv/2605.09468v1/fig-002.webp",
      "caption": "Table 1: Main results comparing CDPR with baselines on the MIntRec and MIntRec2.0 datasets.",
      "page": 6,
      "index": 2,
      "width": 1050,
      "height": 321
    },
    {
      "url": "assets/figures/arxiv/2605.09468v1/fig-003.webp",
      "caption": "Table 2: Ablation studies on MIntRec and MIntRec2.0 datasets. P and L denote pathway and loss function, respectively.",
      "page": 6,
      "index": 3,
      "width": 1050,
      "height": 250
    },
    {
      "url": "assets/figures/arxiv/2605.09468v1/fig-004.webp",
      "caption": "Table 4: Robustness analysis of CDPR and baselines on MIntRec with Gaussian noise injected into the text modality.",
      "page": 7,
      "index": 4,
      "width": 500,
      "height": 283
    },
    {
      "url": "assets/figures/arxiv/2605.09468v1/fig-005.webp",
      "caption": "Table 3: F1-score comparison between CDPR and baselines for intent categories on MIntRec dataset.",
      "page": 7,
      "index": 5,
      "width": 944,
      "height": 321
    },
    {
      "url": "assets/figures/arxiv/2605.09468v1/fig-006.webp",
      "caption": "Figure 3: Qualitative analysis of representative samples from the MIntRec and MIntRec2.0 datasets.",
      "page": 8,
      "index": 6,
      "width": 1024,
      "height": 241
    },
    {
      "url": "assets/figures/arxiv/2605.09468v1/fig-007.webp",
      "caption": "Figure 2: The overall architecture of CDPR. Our approach comprises three key steps: (1) Dual-Pathway Reasoning, which integrates consensus-based intuitive cognition with discrepancy-based deep reasoning to model intricate semantic relations; (2) Inconsistency Perception Mechanism, which mitigates deep semantic conflicts through inconsistency modeling and reliability evaluation; and (3) Multi-View Loss Function, which supervises the training process at different stages.",
      "page": 4,
      "index": 7,
      "width": 1042,
      "height": 504
    }
  ]
}